pulumi_sbercloud/__init__.py
pulumi_sbercloud/_inputs.py
pulumi_sbercloud/_utilities.py
pulumi_sbercloud/aom_service_discovery_rule.py
pulumi_sbercloud/api_gateway_api.py
pulumi_sbercloud/api_gateway_group.py
pulumi_sbercloud/apig_acl_policy.py
pulumi_sbercloud/apig_acl_policy_associate.py
pulumi_sbercloud/apig_api.py
pulumi_sbercloud/apig_api_publishment.py
pulumi_sbercloud/apig_appcode.py
pulumi_sbercloud/apig_application.py
pulumi_sbercloud/apig_application_acl.py
pulumi_sbercloud/apig_application_authorization.py
pulumi_sbercloud/apig_application_quota.py
pulumi_sbercloud/apig_application_quota_associate.py
pulumi_sbercloud/apig_certificate.py
pulumi_sbercloud/apig_channel.py
pulumi_sbercloud/apig_custom_authorizer.py
pulumi_sbercloud/apig_endpoint_connection_management.py
pulumi_sbercloud/apig_endpoint_whitelist.py
pulumi_sbercloud/apig_environment.py
pulumi_sbercloud/apig_environment_variable.py
pulumi_sbercloud/apig_group.py
pulumi_sbercloud/apig_instance.py
pulumi_sbercloud/apig_instance_feature.py
pulumi_sbercloud/apig_instance_routes.py
pulumi_sbercloud/apig_plugin.py
pulumi_sbercloud/apig_plugin_associate.py
pulumi_sbercloud/apig_response.py
pulumi_sbercloud/apig_signature.py
pulumi_sbercloud/apig_signature_associate.py
pulumi_sbercloud/apig_throttling_policy.py
pulumi_sbercloud/apig_throttling_policy_associate.py
pulumi_sbercloud/as_bandwidth_policy.py
pulumi_sbercloud/as_configuration.py
pulumi_sbercloud/as_group.py
pulumi_sbercloud/as_policy.py
pulumi_sbercloud/cbh_asset_agency_authorization.py
pulumi_sbercloud/cbh_ha_instance.py
pulumi_sbercloud/cbh_instance.py
pulumi_sbercloud/cbr_backup_share.py
pulumi_sbercloud/cbr_backup_share_accepter.py
pulumi_sbercloud/cbr_checkpoint.py
pulumi_sbercloud/cbr_policy.py
pulumi_sbercloud/cbr_vault.py
pulumi_sbercloud/cce_addon.py
pulumi_sbercloud/cce_cluster.py
pulumi_sbercloud/cce_namespace.py
pulumi_sbercloud/cce_node.py
pulumi_sbercloud/cce_node_attach.py
pulumi_sbercloud/cce_node_pool.py
pulumi_sbercloud-1.0.0.dist-info/METADATA
pulumi_sbercloud-1.0.0.dist-info/WHEEL
pulumi_sbercloud-1.0.0.dist-info/top_level.txt
pulumi_sbercloud-1.0.0.dist-info/RECORD
